oscat/__init__.py
oscat/cat_os.py
oscat/cat_tree.py
oscat/note_files.py
oscat/setting.py
oscat-0.1.0.dist-info/LICENSE
oscat-0.1.0.dist-info/METADATA
oscat-0.1.0.dist-info/WHEEL
oscat-0.1.0.dist-info/top_level.txt
oscat-0.1.0.dist-info/RECORD
