Metadata-Version: 2.1
Name: oscat
Version: 0.1.0
Summary: A comprehensive library for managing directories and files.
Home-page: https://github.com/abbasfaramarzi/os_cat
Author: Abbas Faramarzi Filabadi
Author-email: abbasfaramarzi@068gmail.com
License: UNKNOWN
Platform: UNKNOWN
Classifier: Development Status :: 3 - Alpha
Classifier: Intended Audience :: Developers
Classifier: License :: OSI Approved :: MIT License
Classifier: Programming Language :: Python :: 3
Classifier: Programming Language :: Python :: 3.6
Classifier: Programming Language :: Python :: 3.7
Classifier: Programming Language :: Python :: 3.8
Classifier: Programming Language :: Python :: 3.9
License-File: LICENSE
Requires-Dist: some-package
